djangoldp_activitypub/__init__.py
djangoldp_activitypub/apps.py
djangoldp_activitypub/models.py
djangoldp_activitypub/views.py
djangoldp_activitypub/activities/__init__.py
djangoldp_activitypub/activities/errors.py
djangoldp_activitypub/activities/objects.py
djangoldp_activitypub/activities/verbs.py
djangoldp_activitypub/endpoints/__init__.py
djangoldp_activitypub/endpoints/webfinger.py
djangoldp_activitypub/management/__init__.py
djangoldp_activitypub/management/commands/__init__.py
djangoldp_activitypub/migrations/0001_initial.py
djangoldp_activitypub/migrations/0002_actor.py
djangoldp_activitypub/migrations/0003_auto_20190822_1338.py
djangoldp_activitypub/migrations/0004_note.py
djangoldp_activitypub/migrations/0005_auto_20190827_1017.py
djangoldp_activitypub/migrations/0006_delete_note.py
djangoldp_activitypub/migrations/0007_auto_20190917_1056.py
djangoldp_activitypub/migrations/__init__.py
djangoldp_activitypub/routing/__init__.py
djangoldp_activitypub/routing/middleware.py
djangoldp_activitypub/routing/urls.py
djangoldp_activitypub/tests/__init__.py
djangoldp_activitypub/tests/models.py
djangoldp_activitypub/tests/runner.py
djangoldp_activitypub/tests/test_actors.py
djangoldp_activitypub/tests/test_follow.py
djangoldp_activitypub/tests/test_inbox.py
djangoldp_activitypub-0.0.1.dist-info/METADATA
djangoldp_activitypub-0.0.1.dist-info/WHEEL
djangoldp_activitypub-0.0.1.dist-info/top_level.txt
djangoldp_activitypub-0.0.1.dist-info/RECORD
